metpy/__init__.py
metpy/_version.py
metpy/_warnings.py
metpy/cbook.py
metpy/deprecation.py
metpy/future.py
metpy/package_tools.py
metpy/pandas.py
metpy/static-data-manifest.txt
metpy/testing.py
metpy/units.py
metpy/xarray.py
metpy/_vendor/__init__.py
metpy/_vendor/xarray.py
metpy/calc/__init__.py
metpy/calc/basic.py
metpy/calc/cross_sections.py
metpy/calc/exceptions.py
metpy/calc/indices.py
metpy/calc/kinematics.py
metpy/calc/thermo.py
metpy/calc/tools.py
metpy/calc/turbulence.py
metpy/constants/__init__.py
metpy/constants/default.py
metpy/constants/nounit.py
metpy/interpolate/__init__.py
metpy/interpolate/geometry.py
metpy/interpolate/grid.py
metpy/interpolate/one_dimension.py
metpy/interpolate/points.py
metpy/interpolate/slices.py
metpy/interpolate/tools.py
metpy/io/__init__.py
metpy/io/_tools.py
metpy/io/gempak.py
metpy/io/gini.py
metpy/io/metar.py
metpy/io/nexrad.py
metpy/io/station_data.py
metpy/io/text.py
metpy/io/_metar_parser/Makefile
metpy/io/_metar_parser/metar_parser.peg
metpy/io/_metar_parser/metar_parser.py
metpy/io/_nexrad_msgs/__init__.py
metpy/io/_nexrad_msgs/msg18.py
metpy/io/_nexrad_msgs/msg3.py
metpy/plots/__init__.py
metpy/plots/_mpl.py
metpy/plots/_util.py
metpy/plots/cartopy_utils.py
metpy/plots/ctables.py
metpy/plots/declarative.py
metpy/plots/mapping.py
metpy/plots/patheffects.py
metpy/plots/plot_areas.py
metpy/plots/skewt.py
metpy/plots/station_plot.py
metpy/plots/wx_symbols.py
metpy/plots/_static/metpy_150x150.png
metpy/plots/_static/metpy_75x75.png
metpy/plots/_static/unidata_150x150.png
metpy/plots/_static/unidata_75x75.png
metpy/plots/colortable_files/Carbone42.tbl
metpy/plots/colortable_files/NWS8bitVel.tbl
metpy/plots/colortable_files/NWSReflectivity.tbl
metpy/plots/colortable_files/NWSReflectivityExpanded.tbl
metpy/plots/colortable_files/NWSSpectrumWidth.tbl
metpy/plots/colortable_files/NWSStormClearReflectivity.tbl
metpy/plots/colortable_files/NWSVelocity.tbl
metpy/plots/colortable_files/WVCIMSS.tbl
MetPy-1.6.3.dist-info/AUTHORS.txt
MetPy-1.6.3.dist-info/LICENSE
MetPy-1.6.3.dist-info/METADATA
MetPy-1.6.3.dist-info/WHEEL
MetPy-1.6.3.dist-info/entry_points.txt
MetPy-1.6.3.dist-info/top_level.txt
MetPy-1.6.3.dist-info/RECORD
