Metadata-Version: 2.1
Name: MetPy
Version: 1.6.3
Summary: Collection of tools for reading, visualizing and performing calculations with weather data.
Maintainer-email: MetPy Developers <support-python@unidata.ucar.edu>
License: BSD-3-Clause
Project-URL: homepage, https://github.com/Unidata/MetPy
Project-URL: Documentation, https://unidata.github.io/MetPy/
Project-URL: Release Notes, https://github.com/Unidata/MetPy/releases
Project-URL: Bug Tracker, https://github.com/Unidata/MetPy/issues
Project-URL: Source Code, https://github.com/Unidata/MetPy
Project-URL: Twitter, https://twitter.com/MetPy
Project-URL: MetPy Mondays, https://www.youtube.com/playlist?list=PLQut5OXpV-0ir4IdllSt1iEZKTwFBa7kO
Keywords: meteorology,weather
Classifier: Development Status :: 5 - Production/Stable
Classifier: Framework :: Matplotlib
Classifier: Programming Language :: Python
Classifier: Programming Language :: Python :: 3.9
Classifier: Programming Language :: Python :: 3.10
Classifier: Programming Language :: Python :: 3.11
Classifier: Programming Language :: Python :: 3.12
Classifier: Topic :: Scientific/Engineering
Classifier: Topic :: Scientific/Engineering :: Atmospheric Science
Classifier: Intended Audience :: Science/Research
Classifier: Operating System :: OS Independent
Classifier: License :: OSI Approved :: BSD License
Requires-Python: >=3.9
License-File: LICENSE
License-File: AUTHORS.txt
Requires-Dist: matplotlib>=3.5.0
Requires-Dist: numpy>=1.20.0
Requires-Dist: pandas>=1.4.0
Requires-Dist: pint>=0.17
Requires-Dist: pooch>=1.2.0
Requires-Dist: pyproj>=3.0.0
Requires-Dist: scipy>=1.8.0
Requires-Dist: traitlets>=5.0.5
Requires-Dist: xarray>=0.21.0
Provides-Extra: doc
Requires-Dist: metpy[examples]; extra == "doc"
Requires-Dist: myst-parser; extra == "doc"
Requires-Dist: netCDF4; extra == "doc"
Requires-Dist: sphinx; extra == "doc"
Requires-Dist: sphinx-gallery>=0.4; extra == "doc"
Requires-Dist: sphinx-design; extra == "doc"
Requires-Dist: pydata-sphinx-theme; extra == "doc"
Provides-Extra: examples
Requires-Dist: geopandas>=0.6.0; extra == "examples"
Requires-Dist: metpy[extras]; extra == "examples"
Provides-Extra: test
Requires-Dist: netCDF4; extra == "test"
Requires-Dist: packaging>=21.0; extra == "test"
Requires-Dist: pytest>=6.2; extra == "test"
Requires-Dist: pytest-mpl; extra == "test"
Provides-Extra: extras
Requires-Dist: cartopy>=0.21.0; extra == "extras"
Requires-Dist: dask>=2020.12.0; extra == "extras"
Requires-Dist: shapely>=1.6.4; extra == "extras"
